lutlib-0.1.2.dist-info/METADATA
lutlib-0.1.2.dist-info/WHEEL
lutlib-0.1.2.dist-info/license_files/LICENSE
lutlib/__init__.py
lutlib/__init__.pyi
lutlib/py.typed
lutlib/lutlib.pypy38-pp73-x86-linux-gnu.so
lutlib-0.1.2.dist-info/RECORD
