Metadata-Version: 2.1
Name: lutlib
Version: 0.1.2
Classifier: Programming Language :: Rust
Classifier: Programming Language :: Python :: Implementation :: CPython
Classifier: Programming Language :: Python :: Implementation :: PyPy
License-File: LICENSE
Summary: A Python library for applying 3D LUTs to images.
Keywords: lut,3dlut,3d-luts
Author: phyng
Author-email: phyngk@gmail.com
Maintainer-email: phyng <phyngk@gmail.com>
Requires-Python: >=3.8
Project-URL: homepage, https://github.com/phyng/lutlib
Project-URL: documentation, https://github.com/phyng/lutlib
Project-URL: repository, https://github.com/phyng/lutlib
